README.md
setup.py
limiter/__init__.py
limiter/exceptions.py
limiter/rate_limit.py
limiter/rate_limiter.py
requests_limiter.egg-info/PKG-INFO
requests_limiter.egg-info/SOURCES.txt
requests_limiter.egg-info/dependency_links.txt
requests_limiter.egg-info/top_level.txt