Metadata-Version: 2.1
Name: requests-limiter
Version: 0.0.1
Summary: UNKNOWN
Home-page: https://github.com/sousa-andre/requests-limiter/
Author: André Sousa
Author-email: andrematosdesousa@gmail.com
License: MIT
Project-URL: Source, https://github.com/sousa-andre/requests-limiter/
Platform: UNKNOWN
